prismui_icon_gen/__init__.py
prismui_icon_gen/cli.py
prismui_icon_gen/generator.py
prismui_icon_gen-0.1.3.dist-info/licenses/LICENSE
prismui_icon_gen-0.1.3.dist-info/METADATA
prismui_icon_gen-0.1.3.dist-info/WHEEL
prismui_icon_gen-0.1.3.dist-info/entry_points.txt
prismui_icon_gen-0.1.3.dist-info/top_level.txt
prismui_icon_gen-0.1.3.dist-info/RECORD
