Metadata-Version: 2.4
Name: prismui-icon-gen
Version: 0.1.3
Summary: A PrismUI tool to generate Python QIcon modules from SVG themes
Author-email: Magicsoldier19 <magicsoldier19@gmail.com>
License: MIT
Project-URL: Homepage, https://github.com/magicsoldier19/prismui-icon-gen
Requires-Python: >=3.8
License-File: LICENSE
Requires-Dist: pyqt5
Dynamic: license-file
